sp/__init__.py
sp/sp.py
spcli-1.0.4.dist-info/LICENSE
spcli-1.0.4.dist-info/METADATA
spcli-1.0.4.dist-info/WHEEL
spcli-1.0.4.dist-info/entry_points.txt
spcli-1.0.4.dist-info/top_level.txt
spcli-1.0.4.dist-info/RECORD
