Metadata-Version: 2.1
Name: spcli
Version: 1.0.4
Summary: Search Startpage.com from the terminal.
Home-page: https://github.com/garee/sp
Author: Gary Blackwood
Author-email: gary@garyblackwood.co.uk
License: GPLv3
Platform: any
Classifier: Development Status :: 5 - Production/Stable
Classifier: Environment :: Console
Classifier: Intended Audience :: Developers
Classifier: Intended Audience :: End Users/Desktop
Classifier: License :: OSI Approved :: GNU General Public License v3 (GPLv3)
Classifier: Operating System :: OS Independent
Classifier: Programming Language :: Python
Classifier: Programming Language :: Python :: 3
Classifier: Programming Language :: Python :: 3 :: Only
Classifier: Programming Language :: Python :: 3.4
Classifier: Programming Language :: Python :: 3.5
Classifier: Programming Language :: Python :: 3.6
Classifier: Programming Language :: Python :: 3.7
Classifier: Topic :: Internet :: WWW/HTTP :: Indexing/Search
Classifier: Topic :: Utilities
Requires-Python: >=3.4
Requires-Dist: colorama (>=0.4.1)
Requires-Dist: lxml (>=4.2.5)
Requires-Dist: pyperclip (>=1.7.0)
Requires-Dist: requests (>=2.20.1)
